jinja_super_macros/__init__.py
jinja_super_macros/env.py
jinja_super_macros/html.py
jinja_super_macros/registry.py
jinja_super_macros/tags.py
jinja_super_macros-0.2.0.dist-info/WHEEL
jinja_super_macros-0.2.0.dist-info/METADATA
jinja_super_macros-0.2.0.dist-info/RECORD
